htms_mid_api/__init__.py
htms_mid_api/htdb.py
htms_mid_api/htms_par_middle.py
htms_mid_api-2.3.1.dist-info/LICENSE
htms_mid_api-2.3.1.dist-info/METADATA
htms_mid_api-2.3.1.dist-info/WHEEL
htms_mid_api-2.3.1.dist-info/top_level.txt
htms_mid_api-2.3.1.dist-info/RECORD
