Metadata-Version: 2.1
Name: htms-mid-api
Version: 2.3.1
Summary: Hyper Table Management System (HTMS) - middle level API
Home-page: https://github.com/Arselon/HTMS
Author: Arslan Aliev
Author-email: arslanaliev@yahoo.com
Maintainer: Arslan Aliev
Maintainer-email: arslanaliev@yahoo.com
License: Apache
Keywords: HTMS,dbms,API,middle level
Platform: UNKNOWN
Classifier: Programming Language :: Python :: 3.7
Classifier: Intended Audience :: Developers
Requires-Python: >=3.7
Requires-Dist: cage-api (>=2.10.0)
Requires-Dist: htms-low-api (>=2.3.1)
